BeginnersbookJavaJiaochengChuyi/README.md
BeginnersbookJavaJiaochengChuyi/__init__.py
BeginnersbookJavaJiaochengChuyi/__main__.py
BeginnersbookJavaJiaochengChuyi/file.epub
BeginnersbookJavaJiaochengChuyi/index.html
BeginnersbookJavaJiaochengChuyi/css/__init__.py
BeginnersbookJavaJiaochengChuyi/css/annotations.css
BeginnersbookJavaJiaochengChuyi/css/main.css
BeginnersbookJavaJiaochengChuyi/css/normalize.css
BeginnersbookJavaJiaochengChuyi/css/popup.css
BeginnersbookJavaJiaochengChuyi/font/__init__.py
BeginnersbookJavaJiaochengChuyi/font/fontello.eot
BeginnersbookJavaJiaochengChuyi/font/fontello.svg
BeginnersbookJavaJiaochengChuyi/font/fontello.ttf
BeginnersbookJavaJiaochengChuyi/font/fontello.woff
BeginnersbookJavaJiaochengChuyi/img/__init__.py
BeginnersbookJavaJiaochengChuyi/img/annotator-glyph-sprite.png
BeginnersbookJavaJiaochengChuyi/img/annotator-icon-sprite.png
BeginnersbookJavaJiaochengChuyi/img/apple-touch-icon.png
BeginnersbookJavaJiaochengChuyi/img/cancelfullscreen.png
BeginnersbookJavaJiaochengChuyi/img/close.png
BeginnersbookJavaJiaochengChuyi/img/fullscreen.png
BeginnersbookJavaJiaochengChuyi/img/loader.gif
BeginnersbookJavaJiaochengChuyi/img/menu-icon.png
BeginnersbookJavaJiaochengChuyi/img/save.png
BeginnersbookJavaJiaochengChuyi/img/saved.png
BeginnersbookJavaJiaochengChuyi/img/settings-s.png
BeginnersbookJavaJiaochengChuyi/img/settings.png
BeginnersbookJavaJiaochengChuyi/img/star.png
BeginnersbookJavaJiaochengChuyi/js/__init__.py
BeginnersbookJavaJiaochengChuyi/js/epub.js
BeginnersbookJavaJiaochengChuyi/js/epub.min.js
BeginnersbookJavaJiaochengChuyi/js/epub.min.map
BeginnersbookJavaJiaochengChuyi/js/hooks.min.js
BeginnersbookJavaJiaochengChuyi/js/hooks.min.map
BeginnersbookJavaJiaochengChuyi/js/reader.js
BeginnersbookJavaJiaochengChuyi/js/reader.js.map
BeginnersbookJavaJiaochengChuyi/js/reader.min.js
BeginnersbookJavaJiaochengChuyi/js/reader.min.map
BeginnersbookJavaJiaochengChuyi/js/hooks/__init__.py
beginnersbook_java_jiaocheng_chuyi-2024.3.4.0.dist-info/METADATA
beginnersbook_java_jiaocheng_chuyi-2024.3.4.0.dist-info/WHEEL
beginnersbook_java_jiaocheng_chuyi-2024.3.4.0.dist-info/entry_points.txt
beginnersbook_java_jiaocheng_chuyi-2024.3.4.0.dist-info/top_level.txt
beginnersbook_java_jiaocheng_chuyi-2024.3.4.0.dist-info/RECORD
